{
  "generated": "2026-07-09T13:08:28.346Z",
  "head_seq": 9922,
  "events_indexed": 6971,
  "observations_returned": 3943,
  "stale_dropped": 1602,
  "new_observations": 17,
  "revisions": 0,
  "tombstoned": 0,
  "duration_ms": 9283,
  "degraded": [
    "resif",
    "noa"
  ],
  "providers": {
    "usgs": {
      "ok": true,
      "http_status": 200,
      "latency_ms": 365,
      "events_returned": 504
    },
    "emsc": {
      "ok": true,
      "http_status": 200,
      "latency_ms": 1774,
      "events_returned": 755
    },
    "geofon": {
      "ok": true,
      "http_status": 200,
      "latency_ms": 988,
      "events_returned": 47
    },
    "ingv": {
      "ok": true,
      "http_status": 200,
      "latency_ms": 1495,
      "events_returned": 102
    },
    "geonet": {
      "ok": true,
      "http_status": 200,
      "latency_ms": 2306,
      "events_returned": 80
    },
    "resif": {
      "ok": false,
      "error": "This operation was aborted"
    },
    "noa": {
      "ok": false,
      "error": "This operation was aborted"
    },
    "ethz": {
      "ok": true,
      "http_status": 200,
      "latency_ms": 2429,
      "events_returned": 6
    },
    "nrcan": {
      "ok": true,
      "http_status": 200,
      "latency_ms": 2479,
      "events_returned": 8
    },
    "ncedc": {
      "ok": true,
      "http_status": 200,
      "latency_ms": 3020,
      "events_returned": 135
    },
    "scedc": {
      "ok": true,
      "http_status": 200,
      "latency_ms": 3011,
      "events_returned": 113
    },
    "knmi": {
      "ok": true,
      "http_status": 204,
      "latency_ms": 2999,
      "events_returned": 0
    },
    "auspass": {
      "ok": true,
      "http_status": 200,
      "latency_ms": 3726,
      "events_returned": 4
    },
    "afad": {
      "ok": true,
      "latency_ms": 4107,
      "events_returned": 175
    },
    "cenc": {
      "ok": true,
      "latency_ms": 5044,
      "events_returned": 635
    },
    "ncs": {
      "ok": true,
      "latency_ms": 6594,
      "events_returned": 150
    },
    "tmd": {
      "ok": true,
      "latency_ms": 6209,
      "events_returned": 20
    },
    "kagsr": {
      "ok": true,
      "latency_ms": 7501,
      "events_returned": 12
    },
    "jma": {
      "ok": true,
      "latency_ms": 6094,
      "events_returned": 204
    },
    "renass": {
      "ok": true,
      "http_status": 200,
      "latency_ms": 7254,
      "events_returned": 89
    },
    "ipgp": {
      "ok": true,
      "http_status": 200,
      "latency_ms": 6889,
      "events_returned": 7
    },
    "usp": {
      "ok": true,
      "http_status": 200,
      "latency_ms": 9061,
      "events_returned": 4
    },
    "lmu": {
      "ok": true,
      "http_status": 204,
      "latency_ms": 7642,
      "events_returned": 0
    },
    "isc": {
      "ok": true,
      "events_returned": 0
    },
    "mexico": {
      "ok": true,
      "latency_ms": 7447,
      "events_returned": 15
    },
    "ipma": {
      "ok": true,
      "latency_ms": 7888,
      "events_returned": 371
    },
    "igp": {
      "ok": true,
      "latency_ms": 7732,
      "events_returned": 429
    },
    "egypt": {
      "ok": true,
      "latency_ms": 8482,
      "events_returned": 30
    },
    "bgs": {
      "ok": true,
      "latency_ms": 8469,
      "events_returned": 48
    }
  }
}
