{
  "generated": "2026-07-11T05:36:45.027Z",
  "head_seq": 13606,
  "events_indexed": 9253,
  "observations_returned": 5211,
  "stale_dropped": 2066,
  "new_observations": 4,
  "revisions": 0,
  "tombstoned": 0,
  "duration_ms": 10843,
  "degraded": [],
  "providers": {
    "usgs": {
      "ok": true,
      "http_status": 200,
      "latency_ms": 179,
      "events_returned": 500
    },
    "emsc": {
      "ok": true,
      "http_status": 200,
      "latency_ms": 2675,
      "events_returned": 677
    },
    "geofon": {
      "ok": true,
      "http_status": 200,
      "latency_ms": 2052,
      "events_returned": 31
    },
    "ingv": {
      "ok": true,
      "http_status": 200,
      "latency_ms": 2771,
      "events_returned": 146
    },
    "geonet": {
      "ok": true,
      "http_status": 200,
      "latency_ms": 2286,
      "events_returned": 93
    },
    "resif": {
      "ok": true,
      "http_status": 200,
      "latency_ms": 9372,
      "events_returned": 73
    },
    "noa": {
      "ok": true,
      "http_status": 200,
      "latency_ms": 4541,
      "events_returned": 150
    },
    "ethz": {
      "ok": true,
      "http_status": 200,
      "latency_ms": 3454,
      "events_returned": 12
    },
    "nrcan": {
      "ok": true,
      "http_status": 200,
      "latency_ms": 3254,
      "events_returned": 12
    },
    "ncedc": {
      "ok": true,
      "http_status": 200,
      "latency_ms": 3524,
      "events_returned": 173
    },
    "scedc": {
      "ok": true,
      "http_status": 200,
      "latency_ms": 3301,
      "events_returned": 130
    },
    "knmi": {
      "ok": true,
      "http_status": 200,
      "latency_ms": 3720,
      "events_returned": 1
    },
    "auspass": {
      "ok": true,
      "http_status": 200,
      "latency_ms": 3774,
      "events_returned": 4
    },
    "afad": {
      "ok": true,
      "latency_ms": 5265,
      "events_returned": 173
    },
    "cenc": {
      "ok": true,
      "latency_ms": 4360,
      "events_returned": 640
    },
    "ncs": {
      "ok": true,
      "latency_ms": 5838,
      "events_returned": 150
    },
    "tmd": {
      "ok": true,
      "latency_ms": 5731,
      "events_returned": 20
    },
    "kagsr": {
      "ok": true,
      "latency_ms": 6691,
      "events_returned": 7
    },
    "bmkg": {
      "ok": true,
      "latency_ms": 5155,
      "events_returned": 28
    },
    "jma": {
      "ok": true,
      "latency_ms": 5225,
      "events_returned": 200
    },
    "renass": {
      "ok": true,
      "http_status": 200,
      "latency_ms": 6807,
      "events_returned": 73
    },
    "ipgp": {
      "ok": true,
      "http_status": 200,
      "latency_ms": 6389,
      "events_returned": 10
    },
    "usp": {
      "ok": true,
      "http_status": 204,
      "latency_ms": 9585,
      "events_returned": 0
    },
    "lmu": {
      "ok": true,
      "http_status": 204,
      "latency_ms": 7025,
      "events_returned": 0
    },
    "isc": {
      "ok": true,
      "events_returned": 0
    },
    "mexico": {
      "ok": true,
      "latency_ms": 6642,
      "events_returned": 15
    },
    "ipma": {
      "ok": true,
      "latency_ms": 7622,
      "events_returned": 385
    },
    "igp": {
      "ok": true,
      "latency_ms": 7151,
      "events_returned": 431
    },
    "egypt": {
      "ok": true,
      "latency_ms": 7645,
      "events_returned": 30
    },
    "bgs": {
      "ok": true,
      "latency_ms": 7711,
      "events_returned": 46
    },
    "ign": {
      "ok": true,
      "latency_ms": 7260,
      "events_returned": 389
    },
    "imo": {
      "ok": true,
      "latency_ms": 10615,
      "events_returned": 165
    },
    "inpres": {
      "ok": true,
      "latency_ms": 8479,
      "events_returned": 30
    },
    "ga": {
      "ok": true,
      "latency_ms": 8013,
      "events_returned": 49
    },
    "ovsicori": {
      "ok": true,
      "latency_ms": 9251,
      "events_returned": 247
    },
    "igepn": {
      "ok": true,
      "latency_ms": 8800,
      "events_returned": 50
    },
    "csn": {
      "ok": true,
      "latency_ms": 8707,
      "events_returned": 39
    },
    "cwa": {
      "ok": true,
      "latency_ms": 9387,
      "events_returned": 32
    }
  }
}
