{
  "generated": "2026-07-09T06:56:31.860Z",
  "head_seq": 9478,
  "events_indexed": 6689,
  "observations_returned": 4055,
  "stale_dropped": 1592,
  "new_observations": 11,
  "revisions": 1,
  "tombstoned": 0,
  "duration_ms": 8483,
  "degraded": [
    "noa"
  ],
  "providers": {
    "usgs": {
      "ok": true,
      "http_status": 200,
      "latency_ms": 214,
      "events_returned": 519
    },
    "emsc": {
      "ok": true,
      "http_status": 200,
      "latency_ms": 2624,
      "events_returned": 750
    },
    "geofon": {
      "ok": true,
      "http_status": 200,
      "latency_ms": 1283,
      "events_returned": 48
    },
    "ingv": {
      "ok": true,
      "http_status": 200,
      "latency_ms": 2214,
      "events_returned": 73
    },
    "geonet": {
      "ok": true,
      "http_status": 200,
      "latency_ms": 2290,
      "events_returned": 90
    },
    "resif": {
      "ok": true,
      "http_status": 200,
      "latency_ms": 7447,
      "events_returned": 83
    },
    "noa": {
      "ok": false,
      "error": "This operation was aborted"
    },
    "ethz": {
      "ok": true,
      "http_status": 200,
      "latency_ms": 2898,
      "events_returned": 4
    },
    "nrcan": {
      "ok": true,
      "http_status": 200,
      "latency_ms": 2721,
      "events_returned": 8
    },
    "ncedc": {
      "ok": true,
      "http_status": 200,
      "latency_ms": 2860,
      "events_returned": 199
    },
    "scedc": {
      "ok": true,
      "http_status": 200,
      "latency_ms": 2747,
      "events_returned": 108
    },
    "knmi": {
      "ok": true,
      "http_status": 204,
      "latency_ms": 3031,
      "events_returned": 0
    },
    "auspass": {
      "ok": true,
      "http_status": 200,
      "latency_ms": 3278,
      "events_returned": 4
    },
    "afad": {
      "ok": true,
      "latency_ms": 3981,
      "events_returned": 164
    },
    "cenc": {
      "ok": true,
      "latency_ms": 3841,
      "events_returned": 635
    },
    "ncs": {
      "ok": true,
      "latency_ms": 5565,
      "events_returned": 150
    },
    "tmd": {
      "ok": true,
      "latency_ms": 5130,
      "events_returned": 20
    },
    "kagsr": {
      "ok": true,
      "latency_ms": 5807,
      "events_returned": 13
    },
    "jma": {
      "ok": true,
      "latency_ms": 4491,
      "events_returned": 199
    },
    "renass": {
      "ok": true,
      "http_status": 200,
      "latency_ms": 5770,
      "events_returned": 83
    },
    "ipgp": {
      "ok": true,
      "http_status": 200,
      "latency_ms": 5568,
      "events_returned": 8
    },
    "usp": {
      "ok": true,
      "http_status": 200,
      "latency_ms": 7653,
      "events_returned": 5
    },
    "lmu": {
      "ok": true,
      "http_status": 204,
      "latency_ms": 6085,
      "events_returned": 0
    },
    "isc": {
      "ok": true,
      "events_returned": 0
    },
    "mexico": {
      "ok": true,
      "latency_ms": 5562,
      "events_returned": 15
    },
    "ipma": {
      "ok": true,
      "latency_ms": 6336,
      "events_returned": 372
    },
    "igp": {
      "ok": true,
      "latency_ms": 6328,
      "events_returned": 427
    },
    "egypt": {
      "ok": true,
      "latency_ms": 8269,
      "events_returned": 30
    },
    "bgs": {
      "ok": true,
      "latency_ms": 6995,
      "events_returned": 48
    }
  }
}
