{
  "generated": "2026-07-08T16:46:38.295Z",
  "head_seq": 8637,
  "events_indexed": 6228,
  "observations_returned": 3872,
  "stale_dropped": 1591,
  "new_observations": 4,
  "revisions": 0,
  "tombstoned": 0,
  "duration_ms": 10903,
  "degraded": [
    "resif",
    "noa",
    "renass",
    "lmu"
  ],
  "providers": {
    "usgs": {
      "ok": true,
      "http_status": 200,
      "latency_ms": 258,
      "events_returned": 498
    },
    "emsc": {
      "ok": true,
      "http_status": 200,
      "latency_ms": 1790,
      "events_returned": 748
    },
    "geofon": {
      "ok": true,
      "http_status": 200,
      "latency_ms": 1110,
      "events_returned": 52
    },
    "ingv": {
      "ok": true,
      "http_status": 200,
      "latency_ms": 1763,
      "events_returned": 86
    },
    "geonet": {
      "ok": true,
      "http_status": 200,
      "latency_ms": 1602,
      "events_returned": 108
    },
    "resif": {
      "ok": false,
      "error": "This operation was aborted"
    },
    "noa": {
      "ok": false,
      "error": "This operation was aborted"
    },
    "ethz": {
      "ok": true,
      "http_status": 200,
      "latency_ms": 2552,
      "events_returned": 7
    },
    "nrcan": {
      "ok": true,
      "http_status": 200,
      "latency_ms": 2623,
      "events_returned": 8
    },
    "ncedc": {
      "ok": true,
      "http_status": 200,
      "latency_ms": 2872,
      "events_returned": 166
    },
    "scedc": {
      "ok": true,
      "http_status": 200,
      "latency_ms": 2883,
      "events_returned": 105
    },
    "knmi": {
      "ok": true,
      "http_status": 204,
      "latency_ms": 3196,
      "events_returned": 0
    },
    "auspass": {
      "ok": true,
      "http_status": 200,
      "latency_ms": 4730,
      "events_returned": 4
    },
    "afad": {
      "ok": true,
      "latency_ms": 4984,
      "events_returned": 170
    },
    "cenc": {
      "ok": true,
      "latency_ms": 5289,
      "events_returned": 632
    },
    "ncs": {
      "ok": true,
      "latency_ms": 7412,
      "events_returned": 150
    },
    "tmd": {
      "ok": true,
      "latency_ms": 6532,
      "events_returned": 20
    },
    "kagsr": {
      "ok": true,
      "latency_ms": 7768,
      "events_returned": 9
    },
    "jma": {
      "ok": true,
      "latency_ms": 6871,
      "events_returned": 200
    },
    "renass": {
      "ok": false,
      "error": "This operation was aborted"
    },
    "ipgp": {
      "ok": true,
      "http_status": 200,
      "latency_ms": 7658,
      "events_returned": 9
    },
    "usp": {
      "ok": true,
      "http_status": 200,
      "latency_ms": 10740,
      "events_returned": 8
    },
    "lmu": {
      "ok": false,
      "error": "This operation was aborted"
    },
    "isc": {
      "ok": true,
      "events_returned": 0
    },
    "mexico": {
      "ok": true,
      "latency_ms": 8162,
      "events_returned": 15
    },
    "ipma": {
      "ok": true,
      "latency_ms": 8903,
      "events_returned": 371
    },
    "igp": {
      "ok": true,
      "latency_ms": 8942,
      "events_returned": 427
    },
    "egypt": {
      "ok": true,
      "latency_ms": 10721,
      "events_returned": 30
    },
    "bgs": {
      "ok": true,
      "latency_ms": 9345,
      "events_returned": 49
    }
  }
}
