{
  "generated": "2026-07-15T22:31:33.748Z",
  "head_seq": 23252,
  "events_indexed": 12630,
  "observations_returned": 5486,
  "stale_dropped": 2236,
  "new_observations": 3,
  "revisions": 0,
  "tombstoned": 0,
  "duration_ms": 22871,
  "degraded": [],
  "providers": {
    "usgs": {
      "ok": true,
      "http_status": 200,
      "latency_ms": 299,
      "events_returned": 605
    },
    "emsc": {
      "ok": true,
      "http_status": 200,
      "latency_ms": 1568,
      "events_returned": 752
    },
    "geofon": {
      "ok": true,
      "http_status": 200,
      "latency_ms": 915,
      "events_returned": 39
    },
    "ingv": {
      "ok": true,
      "http_status": 200,
      "latency_ms": 1416,
      "events_returned": 108
    },
    "geonet": {
      "ok": true,
      "http_status": 200,
      "latency_ms": 2033,
      "events_returned": 119
    },
    "resif": {
      "ok": true,
      "http_status": 200,
      "latency_ms": 9518,
      "events_returned": 77
    },
    "noa": {
      "ok": true,
      "http_status": 200,
      "latency_ms": 7024,
      "events_returned": 131
    },
    "ethz": {
      "ok": true,
      "http_status": 200,
      "latency_ms": 2029,
      "events_returned": 10
    },
    "nrcan": {
      "ok": true,
      "http_status": 200,
      "latency_ms": 2211,
      "events_returned": 7
    },
    "ncedc": {
      "ok": true,
      "http_status": 200,
      "latency_ms": 2954,
      "events_returned": 214
    },
    "scedc": {
      "ok": true,
      "http_status": 200,
      "latency_ms": 2755,
      "events_returned": 154
    },
    "knmi": {
      "ok": true,
      "http_status": 200,
      "latency_ms": 2938,
      "events_returned": 1
    },
    "auspass": {
      "ok": true,
      "http_status": 200,
      "latency_ms": 3945,
      "events_returned": 4
    },
    "afad": {
      "ok": true,
      "latency_ms": 4691,
      "events_returned": 190
    },
    "cenc": {
      "ok": true,
      "latency_ms": 5516,
      "events_returned": 657
    },
    "ncs": {
      "ok": true,
      "latency_ms": 7749,
      "events_returned": 150
    },
    "tmd": {
      "ok": true,
      "latency_ms": 6827,
      "events_returned": 20
    },
    "kagsr": {
      "ok": true,
      "latency_ms": 7950,
      "events_returned": 15
    },
    "bmkg": {
      "ok": true,
      "latency_ms": 5997,
      "events_returned": 27
    },
    "jma": {
      "ok": true,
      "latency_ms": 6095,
      "events_returned": 194
    },
    "renass": {
      "ok": true,
      "http_status": 200,
      "latency_ms": 7137,
      "events_returned": 77
    },
    "ipgp": {
      "ok": true,
      "http_status": 200,
      "latency_ms": 7226,
      "events_returned": 25
    },
    "usp": {
      "ok": true,
      "http_status": 200,
      "latency_ms": 9685,
      "events_returned": 14
    },
    "lmu": {
      "ok": true,
      "http_status": 204,
      "latency_ms": 7727,
      "events_returned": 0
    },
    "isc": {
      "ok": true,
      "events_returned": 0
    },
    "mexico": {
      "ok": true,
      "latency_ms": 22548,
      "events_returned": 15
    },
    "ipma": {
      "ok": true,
      "latency_ms": 7876,
      "events_returned": 399
    },
    "igp": {
      "ok": true,
      "latency_ms": 7551,
      "events_returned": 450
    },
    "egypt": {
      "ok": true,
      "latency_ms": 8160,
      "events_returned": 30
    },
    "bgs": {
      "ok": true,
      "latency_ms": 8001,
      "events_returned": 46
    },
    "ign": {
      "ok": true,
      "latency_ms": 8481,
      "events_returned": 383
    },
    "imo": {
      "ok": true,
      "latency_ms": 9030,
      "events_returned": 84
    },
    "inpres": {
      "ok": true,
      "latency_ms": 8806,
      "events_returned": 30
    },
    "ga": {
      "ok": true,
      "latency_ms": 9520,
      "events_returned": 49
    },
    "ovsicori": {
      "ok": true,
      "latency_ms": 9633,
      "events_returned": 253
    },
    "igepn": {
      "ok": true,
      "latency_ms": 9319,
      "events_returned": 50
    },
    "csn": {
      "ok": true,
      "latency_ms": 8890,
      "events_returned": 75
    },
    "cwa": {
      "ok": true,
      "latency_ms": 10626,
      "events_returned": 32
    }
  }
}
