{
  "generated": "2026-07-08T17:16:37.024Z",
  "head_seq": 8657,
  "events_indexed": 6242,
  "observations_returned": 3855,
  "stale_dropped": 1591,
  "new_observations": 4,
  "revisions": 0,
  "tombstoned": 0,
  "duration_ms": 10222,
  "degraded": [
    "resif",
    "noa",
    "renass",
    "ipgp",
    "lmu"
  ],
  "providers": {
    "usgs": {
      "ok": true,
      "http_status": 200,
      "latency_ms": 280,
      "events_returned": 498
    },
    "emsc": {
      "ok": true,
      "http_status": 200,
      "latency_ms": 2360,
      "events_returned": 742
    },
    "geofon": {
      "ok": true,
      "http_status": 200,
      "latency_ms": 1090,
      "events_returned": 49
    },
    "ingv": {
      "ok": true,
      "http_status": 200,
      "latency_ms": 1744,
      "events_returned": 86
    },
    "geonet": {
      "ok": true,
      "http_status": 200,
      "latency_ms": 2314,
      "events_returned": 104
    },
    "resif": {
      "ok": false,
      "error": "This operation was aborted"
    },
    "noa": {
      "ok": false,
      "error": "This operation was aborted"
    },
    "ethz": {
      "ok": true,
      "http_status": 200,
      "latency_ms": 2852,
      "events_returned": 7
    },
    "nrcan": {
      "ok": true,
      "http_status": 200,
      "latency_ms": 3052,
      "events_returned": 8
    },
    "ncedc": {
      "ok": true,
      "http_status": 200,
      "latency_ms": 3407,
      "events_returned": 170
    },
    "scedc": {
      "ok": true,
      "http_status": 200,
      "latency_ms": 3493,
      "events_returned": 106
    },
    "knmi": {
      "ok": true,
      "http_status": 204,
      "latency_ms": 3838,
      "events_returned": 0
    },
    "auspass": {
      "ok": true,
      "http_status": 200,
      "latency_ms": 4418,
      "events_returned": 4
    },
    "afad": {
      "ok": true,
      "latency_ms": 5446,
      "events_returned": 170
    },
    "cenc": {
      "ok": true,
      "latency_ms": 6830,
      "events_returned": 632
    },
    "ncs": {
      "ok": true,
      "latency_ms": 8302,
      "events_returned": 150
    },
    "tmd": {
      "ok": true,
      "latency_ms": 8012,
      "events_returned": 20
    },
    "kagsr": {
      "ok": true,
      "latency_ms": 8803,
      "events_returned": 9
    },
    "jma": {
      "ok": true,
      "latency_ms": 7255,
      "events_returned": 200
    },
    "renass": {
      "ok": false,
      "error": "This operation was aborted"
    },
    "ipgp": {
      "ok": false,
      "error": "This operation was aborted"
    },
    "usp": {
      "ok": true,
      "http_status": 200,
      "latency_ms": 10051,
      "events_returned": 8
    },
    "lmu": {
      "ok": false,
      "error": "This operation was aborted"
    },
    "isc": {
      "ok": true,
      "events_returned": 0
    },
    "mexico": {
      "ok": true,
      "latency_ms": 8884,
      "events_returned": 15
    },
    "ipma": {
      "ok": true,
      "latency_ms": 9550,
      "events_returned": 371
    },
    "igp": {
      "ok": true,
      "latency_ms": 9210,
      "events_returned": 427
    },
    "egypt": {
      "ok": true,
      "latency_ms": 9446,
      "events_returned": 30
    },
    "bgs": {
      "ok": true,
      "latency_ms": 9550,
      "events_returned": 49
    }
  }
}
