{
  "generated": "2026-07-17T11:50:37.404Z",
  "head_seq": 26822,
  "events_indexed": 12566,
  "observations_returned": 5540,
  "stale_dropped": 2254,
  "new_observations": 5,
  "revisions": 1,
  "tombstoned": 0,
  "duration_ms": 10732,
  "degraded": [
    "scedc"
  ],
  "providers": {
    "usgs": {
      "ok": true,
      "http_status": 200,
      "latency_ms": 755,
      "events_returned": 614
    },
    "emsc": {
      "ok": true,
      "http_status": 200,
      "latency_ms": 2309,
      "events_returned": 798
    },
    "geofon": {
      "ok": true,
      "http_status": 200,
      "latency_ms": 1151,
      "events_returned": 48
    },
    "ingv": {
      "ok": true,
      "http_status": 200,
      "latency_ms": 1472,
      "events_returned": 95
    },
    "geonet": {
      "ok": true,
      "http_status": 200,
      "latency_ms": 1628,
      "events_returned": 158
    },
    "resif": {
      "ok": true,
      "http_status": 200,
      "latency_ms": 8005,
      "events_returned": 99
    },
    "noa": {
      "ok": true,
      "http_status": 200,
      "latency_ms": 3166,
      "events_returned": 129
    },
    "ethz": {
      "ok": true,
      "http_status": 200,
      "latency_ms": 2487,
      "events_returned": 6
    },
    "nrcan": {
      "ok": true,
      "http_status": 200,
      "latency_ms": 2071,
      "events_returned": 13
    },
    "ncedc": {
      "ok": true,
      "http_status": 200,
      "latency_ms": 2139,
      "events_returned": 184
    },
    "scedc": {
      "ok": false,
      "error": "fetch failed"
    },
    "knmi": {
      "ok": true,
      "http_status": 204,
      "latency_ms": 2444,
      "events_returned": 0
    },
    "auspass": {
      "ok": true,
      "http_status": 200,
      "latency_ms": 5185,
      "events_returned": 4
    },
    "afad": {
      "ok": true,
      "latency_ms": 3943,
      "events_returned": 207
    },
    "cenc": {
      "ok": true,
      "latency_ms": 3512,
      "events_returned": 661
    },
    "ncs": {
      "ok": true,
      "latency_ms": 5062,
      "events_returned": 150
    },
    "tmd": {
      "ok": true,
      "latency_ms": 4136,
      "events_returned": 20
    },
    "kagsr": {
      "ok": true,
      "latency_ms": 5709,
      "events_returned": 9
    },
    "bmkg": {
      "ok": true,
      "latency_ms": 3408,
      "events_returned": 27
    },
    "jma": {
      "ok": true,
      "latency_ms": 3485,
      "events_returned": 189
    },
    "renass": {
      "ok": true,
      "http_status": 200,
      "latency_ms": 4639,
      "events_returned": 99
    },
    "ipgp": {
      "ok": true,
      "http_status": 200,
      "latency_ms": 4719,
      "events_returned": 21
    },
    "usp": {
      "ok": true,
      "http_status": 200,
      "latency_ms": 8243,
      "events_returned": 4
    },
    "lmu": {
      "ok": true,
      "http_status": 204,
      "latency_ms": 5511,
      "events_returned": 0
    },
    "isc": {
      "ok": true,
      "events_returned": 0
    },
    "mexico": {
      "ok": true,
      "latency_ms": 4967,
      "events_returned": 15
    },
    "ipma": {
      "ok": true,
      "latency_ms": 5749,
      "events_returned": 398
    },
    "igp": {
      "ok": true,
      "latency_ms": 5743,
      "events_returned": 460
    },
    "egypt": {
      "ok": true,
      "latency_ms": 6180,
      "events_returned": 30
    },
    "bgs": {
      "ok": true,
      "latency_ms": 5957,
      "events_returned": 44
    },
    "ign": {
      "ok": true,
      "latency_ms": 7075,
      "events_returned": 398
    },
    "imo": {
      "ok": true,
      "latency_ms": 6635,
      "events_returned": 162
    },
    "inpres": {
      "ok": true,
      "latency_ms": 7115,
      "events_returned": 30
    },
    "ga": {
      "ok": true,
      "latency_ms": 6227,
      "events_returned": 54
    },
    "ovsicori": {
      "ok": true,
      "latency_ms": 8187,
      "events_returned": 273
    },
    "igepn": {
      "ok": true,
      "latency_ms": 7382,
      "events_returned": 50
    },
    "csn": {
      "ok": true,
      "latency_ms": 6962,
      "events_returned": 59
    },
    "cwa": {
      "ok": true,
      "latency_ms": 7994,
      "events_returned": 32
    }
  }
}
