{
  "generated": "2026-07-16T20:21:29.343Z",
  "head_seq": 25454,
  "events_indexed": 12845,
  "observations_returned": 5604,
  "stale_dropped": 2251,
  "new_observations": 12,
  "revisions": 0,
  "tombstoned": 0,
  "duration_ms": 19554,
  "degraded": [],
  "providers": {
    "usgs": {
      "ok": true,
      "http_status": 200,
      "latency_ms": 302,
      "events_returned": 635
    },
    "emsc": {
      "ok": true,
      "http_status": 200,
      "latency_ms": 1740,
      "events_returned": 771
    },
    "geofon": {
      "ok": true,
      "http_status": 200,
      "latency_ms": 961,
      "events_returned": 37
    },
    "ingv": {
      "ok": true,
      "http_status": 200,
      "latency_ms": 1450,
      "events_returned": 97
    },
    "geonet": {
      "ok": true,
      "http_status": 200,
      "latency_ms": 1968,
      "events_returned": 154
    },
    "resif": {
      "ok": true,
      "http_status": 200,
      "latency_ms": 8218,
      "events_returned": 105
    },
    "noa": {
      "ok": true,
      "http_status": 200,
      "latency_ms": 3705,
      "events_returned": 143
    },
    "ethz": {
      "ok": true,
      "http_status": 200,
      "latency_ms": 2281,
      "events_returned": 7
    },
    "nrcan": {
      "ok": true,
      "http_status": 200,
      "latency_ms": 2207,
      "events_returned": 13
    },
    "ncedc": {
      "ok": true,
      "http_status": 200,
      "latency_ms": 2579,
      "events_returned": 192
    },
    "scedc": {
      "ok": true,
      "http_status": 200,
      "latency_ms": 2570,
      "events_returned": 119
    },
    "knmi": {
      "ok": true,
      "http_status": 204,
      "latency_ms": 2688,
      "events_returned": 0
    },
    "auspass": {
      "ok": true,
      "http_status": 200,
      "latency_ms": 3255,
      "events_returned": 4
    },
    "afad": {
      "ok": true,
      "latency_ms": 3944,
      "events_returned": 173
    },
    "cenc": {
      "ok": true,
      "latency_ms": 4113,
      "events_returned": 659
    },
    "ncs": {
      "ok": true,
      "latency_ms": 5750,
      "events_returned": 150
    },
    "tmd": {
      "ok": true,
      "latency_ms": 5308,
      "events_returned": 20
    },
    "kagsr": {
      "ok": true,
      "latency_ms": 6460,
      "events_returned": 10
    },
    "bmkg": {
      "ok": true,
      "latency_ms": 5094,
      "events_returned": 27
    },
    "jma": {
      "ok": true,
      "latency_ms": 4640,
      "events_returned": 189
    },
    "renass": {
      "ok": true,
      "http_status": 200,
      "latency_ms": 5746,
      "events_returned": 105
    },
    "ipgp": {
      "ok": true,
      "http_status": 200,
      "latency_ms": 5471,
      "events_returned": 20
    },
    "usp": {
      "ok": true,
      "http_status": 200,
      "latency_ms": 8618,
      "events_returned": 8
    },
    "lmu": {
      "ok": true,
      "http_status": 204,
      "latency_ms": 5904,
      "events_returned": 0
    },
    "isc": {
      "ok": true,
      "events_returned": 0
    },
    "mexico": {
      "ok": true,
      "latency_ms": 19292,
      "events_returned": 15
    },
    "ipma": {
      "ok": true,
      "latency_ms": 6087,
      "events_returned": 396
    },
    "igp": {
      "ok": true,
      "latency_ms": 5901,
      "events_returned": 457
    },
    "egypt": {
      "ok": true,
      "latency_ms": 6647,
      "events_returned": 30
    },
    "bgs": {
      "ok": true,
      "latency_ms": 6498,
      "events_returned": 45
    },
    "ign": {
      "ok": true,
      "latency_ms": 6092,
      "events_returned": 393
    },
    "imo": {
      "ok": true,
      "latency_ms": 7262,
      "events_returned": 108
    },
    "inpres": {
      "ok": true,
      "latency_ms": 7700,
      "events_returned": 30
    },
    "ga": {
      "ok": true,
      "latency_ms": 8200,
      "events_returned": 52
    },
    "ovsicori": {
      "ok": true,
      "latency_ms": 8479,
      "events_returned": 272
    },
    "igepn": {
      "ok": true,
      "latency_ms": 8197,
      "events_returned": 50
    },
    "csn": {
      "ok": true,
      "latency_ms": 7645,
      "events_returned": 86
    },
    "cwa": {
      "ok": true,
      "latency_ms": 8955,
      "events_returned": 32
    }
  }
}
