{
  "generated": "2026-07-13T06:35:57.912Z",
  "head_seq": 17338,
  "events_indexed": 11070,
  "observations_returned": 4927,
  "stale_dropped": 2094,
  "new_observations": 11,
  "revisions": 0,
  "tombstoned": 0,
  "duration_ms": 15235,
  "degraded": [
    "noa"
  ],
  "providers": {
    "usgs": {
      "ok": true,
      "http_status": 200,
      "latency_ms": 227,
      "events_returned": 465
    },
    "emsc": {
      "ok": true,
      "http_status": 200,
      "latency_ms": 1308,
      "events_returned": 699
    },
    "geofon": {
      "ok": true,
      "http_status": 200,
      "latency_ms": 971,
      "events_returned": 26
    },
    "ingv": {
      "ok": true,
      "http_status": 200,
      "latency_ms": 1546,
      "events_returned": 109
    },
    "geonet": {
      "ok": true,
      "http_status": 200,
      "latency_ms": 1788,
      "events_returned": 180
    },
    "resif": {
      "ok": true,
      "http_status": 200,
      "latency_ms": 10078,
      "events_returned": 25
    },
    "noa": {
      "ok": false,
      "error": "This operation was aborted"
    },
    "ethz": {
      "ok": true,
      "http_status": 200,
      "latency_ms": 2095,
      "events_returned": 1
    },
    "nrcan": {
      "ok": true,
      "http_status": 204,
      "latency_ms": 2200,
      "events_returned": 0
    },
    "ncedc": {
      "ok": true,
      "http_status": 200,
      "latency_ms": 2964,
      "events_returned": 189
    },
    "scedc": {
      "ok": true,
      "http_status": 200,
      "latency_ms": 2771,
      "events_returned": 107
    },
    "knmi": {
      "ok": true,
      "http_status": 204,
      "latency_ms": 2981,
      "events_returned": 0
    },
    "auspass": {
      "ok": true,
      "http_status": 200,
      "latency_ms": 3969,
      "events_returned": 4
    },
    "afad": {
      "ok": true,
      "latency_ms": 4057,
      "events_returned": 157
    },
    "cenc": {
      "ok": true,
      "latency_ms": 5297,
      "events_returned": 650
    },
    "ncs": {
      "ok": true,
      "latency_ms": 6830,
      "events_returned": 150
    },
    "tmd": {
      "ok": true,
      "latency_ms": 6594,
      "events_returned": 20
    },
    "kagsr": {
      "ok": true,
      "latency_ms": 8969,
      "events_returned": 14
    },
    "bmkg": {
      "ok": true,
      "latency_ms": 6451,
      "events_returned": 26
    },
    "jma": {
      "ok": true,
      "latency_ms": 6117,
      "events_returned": 195
    },
    "renass": {
      "ok": true,
      "http_status": 200,
      "latency_ms": 6981,
      "events_returned": 25
    },
    "ipgp": {
      "ok": true,
      "http_status": 200,
      "latency_ms": 7228,
      "events_returned": 14
    },
    "usp": {
      "ok": true,
      "http_status": 200,
      "latency_ms": 10456,
      "events_returned": 1
    },
    "lmu": {
      "ok": true,
      "http_status": 204,
      "latency_ms": 8050,
      "events_returned": 0
    },
    "isc": {
      "ok": true,
      "events_returned": 0
    },
    "mexico": {
      "ok": true,
      "latency_ms": 7639,
      "events_returned": 15
    },
    "ipma": {
      "ok": true,
      "latency_ms": 8216,
      "events_returned": 407
    },
    "igp": {
      "ok": true,
      "latency_ms": 8140,
      "events_returned": 436
    },
    "egypt": {
      "ok": true,
      "latency_ms": 8716,
      "events_returned": 30
    },
    "bgs": {
      "ok": true,
      "latency_ms": 8523,
      "events_returned": 42
    },
    "ign": {
      "ok": true,
      "latency_ms": 8266,
      "events_returned": 387
    },
    "imo": {
      "ok": true,
      "latency_ms": 9529,
      "events_returned": 92
    },
    "inpres": {
      "ok": true,
      "latency_ms": 9370,
      "events_returned": 30
    },
    "ga": {
      "ok": true,
      "latency_ms": 9652,
      "events_returned": 49
    },
    "ovsicori": {
      "ok": true,
      "latency_ms": 10104,
      "events_returned": 252
    },
    "igepn": {
      "ok": true,
      "latency_ms": 9813,
      "events_returned": 50
    },
    "csn": {
      "ok": true,
      "latency_ms": 9500,
      "events_returned": 48
    },
    "cwa": {
      "ok": true,
      "latency_ms": 11031,
      "events_returned": 32
    }
  }
}
